Kronos/__init__.py
Kronos/converters.py
Kronos/costructors.py
Kronos/hourglass.py
Kronos/periods.py
Kronos/sliders.py
Kronos/timezones.py
Kronos/version.py
xautomata_kronos-6.1.1.dist-info/licenses/LICENSE
xautomata_kronos-6.1.1.dist-info/METADATA
xautomata_kronos-6.1.1.dist-info/WHEEL
xautomata_kronos-6.1.1.dist-info/top_level.txt
xautomata_kronos-6.1.1.dist-info/RECORD
