Metadata-Version: 2.4
Name: xautomata-kronos
Version: 6.1.1
Home-page: https://github.com/sherlogic/xautomata-kronos.git
Author: Andrea Jacassi
Author-email: 
License: MIT
Requires-Python: >=3.8.0
License-File: LICENSE
Requires-Dist: pytz==2022.7
Dynamic: author
Dynamic: description
Dynamic: description-content-type
Dynamic: home-page
Dynamic: license
Dynamic: license-file
Dynamic: requires-dist
Dynamic: requires-python
